archetypes.schemaextender-3.0.1-py2.7-nspkg.pth
archetypes/schemaextender/TODO.txt
archetypes/schemaextender/__init__.py
archetypes/schemaextender/benchmark.py
archetypes/schemaextender/caching.zcml
archetypes/schemaextender/configure.zcml
archetypes/schemaextender/extender.py
archetypes/schemaextender/field.py
archetypes/schemaextender/implements.zcml
archetypes/schemaextender/interfaces.py
archetypes/schemaextender/usage.txt
archetypes/schemaextender/tests/__init__.py
archetypes/schemaextender/tests/base.py
archetypes/schemaextender/tests/mocks.py
archetypes/schemaextender/tests/testAccessor.py
archetypes/schemaextender/tests/testIntegration.py
archetypes/schemaextender/tests/testOrdering.py
archetypes/schemaextender/tests/testSchemaFactory.py
archetypes.schemaextender-3.0.1.dist-info/METADATA
archetypes.schemaextender-3.0.1.dist-info/WHEEL
archetypes.schemaextender-3.0.1.dist-info/entry_points.txt
archetypes.schemaextender-3.0.1.dist-info/namespace_packages.txt
archetypes.schemaextender-3.0.1.dist-info/top_level.txt
archetypes.schemaextender-3.0.1.dist-info/RECORD
