Metadata-Version: 2.1
Name: archetypes.schemaextender
Version: 3.0.1
Summary: Dynamically extend Archetypes schemas with named adapters.
Home-page: https://pypi.org/project/archetypes.schemaextender
Author: Florian Schulze
Author-email: plone-developers@lists.sourceforge.net
License: GPL
Keywords: Archetypes Schema extend
Platform: UNKNOWN
Classifier: Development Status :: 6 - Mature
Classifier: Framework :: Plone
Classifier: Framework :: Plone :: 5.2
Classifier: Framework :: Plone :: Core
Classifier: Framework :: Zope2
Classifier: Framework :: Zope :: 4
Classifier: License :: OSI Approved :: GNU General Public License (GPL)
Classifier: Programming Language :: Python
Classifier: Programming Language :: Python :: 2.7
Requires-Dist: setuptools
Requires-Dist: six
Requires-Dist: plone.uuid
